areport/__init__.py
areport/report.py
areport/utils.py
areport-1.0.37.dist-info/licenses/LICENSE
areport-1.0.37.dist-info/METADATA
areport-1.0.37.dist-info/WHEEL
areport-1.0.37.dist-info/top_level.txt
areport-1.0.37.dist-info/RECORD
