Metadata-Version: 2.4
Name: areport
Version: 1.0.37
License: MIT License
Classifier: License :: OSI Approved :: MIT License
Classifier: Programming Language :: Python
Classifier: Programming Language :: Python :: 3
Requires-Python: >=3.10
License-File: LICENSE
Requires-Dist: pandas>=2.1.3
Dynamic: license-file
